MANIFEST.in
setup.cfg
setup.py
microcosm_propertygraph/__init__.py
microcosm_propertygraph/neo4j.py
microcosm_propertygraph.egg-info/PKG-INFO
microcosm_propertygraph.egg-info/SOURCES.txt
microcosm_propertygraph.egg-info/dependency_links.txt
microcosm_propertygraph.egg-info/entry_points.txt
microcosm_propertygraph.egg-info/not-zip-safe
microcosm_propertygraph.egg-info/requires.txt
microcosm_propertygraph.egg-info/top_level.txt
microcosm_propertygraph/models/__init__.py
microcosm_propertygraph/models/node.py
microcosm_propertygraph/models/relationship.py
microcosm_propertygraph/stores/__init__.py
microcosm_propertygraph/stores/base.py
microcosm_propertygraph/stores/node_store.py
microcosm_propertygraph/stores/relationship_store.py