Metadata-Version: 1.0
Name: microcosm-propertygraph
Version: 1.1.0
Summary: Microcosm Property graph - Conventions for exposing data as a property graph
Home-page: https://github.com/globality-corp/microcosm
Author: Globality Engineering
Author-email: engineering@globality.com
License: UNKNOWN
Keywords: microcosm
Platform: UNKNOWN
